corvy_sdk/__init__.py
corvy_sdk/command_parsing.py
corvy_sdk/corvybot.py
corvy_sdk/default_logger.py
corvy_sdk/flock.py
corvy_sdk/messages.py
corvy_sdk/nest.py
corvy_sdk/state.py
corvy_sdk/user.py
corvy_sdk-2.3.1.dist-info/METADATA
corvy_sdk-2.3.1.dist-info/WHEEL
corvy_sdk-2.3.1.dist-info/top_level.txt
corvy_sdk-2.3.1.dist-info/RECORD
