Metadata-Version: 2.4
Name: corvy_sdk
Version: 2.3.1
Summary: An officially sponsored, community maintained SDK for Corvy.
Author-email: SimuCorps Team <contact@simucorps.org>
License-Expression: GPL-3.0-or-later
Keywords: CORVY
Classifier: Development Status :: 4 - Beta
Classifier: Intended Audience :: Developers
Classifier: Programming Language :: Python :: 3
Classifier: Programming Language :: Python :: 3.9
Classifier: Programming Language :: Python :: 3.10
Classifier: Programming Language :: Python :: 3.11
Classifier: Programming Language :: Python :: 3.12
Classifier: Programming Language :: Python :: 3.13
Requires-Python: >=3.9
Requires-Dist: aiohttp>=3.11
Requires-Dist: websockets>=15.0
